MANIFEST.in
README.rst
setup.py
mdeditor/__init__.py
mdeditor/inlinecss.py
mdeditor/markdown_editor.py
mdeditor/syncevernote.py
mdeditor.egg-info/PKG-INFO
mdeditor.egg-info/SOURCES.txt
mdeditor.egg-info/dependency_links.txt
mdeditor.egg-info/entry_points.txt
mdeditor.egg-info/requires.txt
mdeditor.egg-info/top_level.txt
mdeditor/static/main.css
mdeditor/static/main.js
mdeditor/static/lib/css/codemirror.css
mdeditor/static/lib/css/markdown.css
mdeditor/static/lib/css/markdown_edit.css
mdeditor/static/lib/css/neat.css
mdeditor/static/lib/css/pygments.css
mdeditor/static/lib/css/semantic.min.css
mdeditor/static/lib/css/themes/default/assets/fonts/icons.eot
mdeditor/static/lib/css/themes/default/assets/fonts/icons.otf
mdeditor/static/lib/css/themes/default/assets/fonts/icons.svg
mdeditor/static/lib/css/themes/default/assets/fonts/icons.ttf
mdeditor/static/lib/css/themes/default/assets/fonts/icons.woff
mdeditor/static/lib/css/themes/default/assets/fonts/icons.woff2
mdeditor/static/lib/fonts/glyphicons-halflings-regular.ttf
mdeditor/static/lib/fonts/glyphicons-halflings-regular.woff
mdeditor/static/lib/fonts/glyphicons-halflings-regular.woff2
mdeditor/static/lib/js/bootstrap.min.js
mdeditor/static/lib/js/codemirror.js
mdeditor/static/lib/js/jquery.min.js
mdeditor/static/lib/js/markdown.js
mdeditor/static/lib/js/semantic.min.js
mdeditor/templates/docs.html
mdeditor/templates/error.html
mdeditor/templates/home.html
mdeditor/templates/preview.html