Metadata-Version: 1.0
Name: mdeditor
Version: 0.3.2
Summary: markdown editor web
Home-page: https://github.com/kghch/md_editor
Author: kghch
Author-email: wanghan0307@gmail.com
License: UNKNOWN
Platform: UNKNOWN
